arc/__init__.py
arc/_database.py
arc/alkali_atom_data.py
arc/alkali_atom_functions.py
arc/arc_c_extensions.c
arc/arc_c_extensions.cpython-314-x86_64-linux-musl.so
arc/arc_c_extensions.py
arc/beta.py
arc/calculations_atom_pairstate.py
arc/calculations_atom_single.py
arc/divalent_atom_data.py
arc/divalent_atom_functions.py
arc/materials.py
arc/setupc.py
arc/web_functionality.py
arc/wigner.py
arc/advanced/__init__.py
arc/advanced/population_lifetime.py
arc/data/NIST_cs_dipole_matrix_elements.npy
arc/data/NIST_cs_quadrupole_matrix_elements.npy
arc/data/NIST_k_dipole_matrix_elements.npy
arc/data/NIST_k_quadrupole_matrix_elements.npy
arc/data/NIST_li6_dipole_matrix_elements.npy
arc/data/NIST_li6_quadrupole_matrix_elements.npy
arc/data/NIST_li7_dipole_matrix_elements.npy
arc/data/NIST_li7_quadrupole_matrix_elements.npy
arc/data/NIST_na23_dipole_matrix_elements.npy
arc/data/NIST_na23_quadrupole_matrix_elements.npy
arc/data/NIST_rb_dipole_matrix_elements.npy
arc/data/NIST_rb_quadrupole_matrix_elements.npy
arc/data/angularMatrix.npy
arc/data/angularMatrix_meta.npy
arc/data/ca_dipole_matrix_elements.npy
arc/data/ca_level_data.csv
arc/data/ca_quadrupole_matrix_elements.npy
arc/data/caesium_literature_dme.csv
arc/data/calcium_literature_dme.csv
arc/data/cs_NIST_level_data.ascii
arc/data/cs_dipole_matrix_elements.npy
arc/data/cs_hfs_data.csv
arc/data/cs_quadrupole_matrix_elements.npy
arc/data/h_NIST_level_data.ascii
arc/data/h_dipole_matrix_elements.npy
arc/data/h_quadrupole_matrix_elements.npy
arc/data/k39_hfs_data.csv
arc/data/k40_hfs_data.csv
arc/data/k41_hfs_data.csv
arc/data/k_NIST_level_data.ascii
arc/data/k_dipole_matrix_elements.npy
arc/data/k_quadrupole_matrix_elements.npy
arc/data/li6_dipole_matrix_elements.npy
arc/data/li6_hfs_data.csv
arc/data/li6_quadrupole_matrix_elements.npy
arc/data/li7_dipole_matrix_elements.npy
arc/data/li7_hfs_data.csv
arc/data/li7_quadrupole_matrix_elements.npy
arc_alkali_rydberg_calculator-3.10.2.dist-info/METADATA
arc_alkali_rydberg_calculator-3.10.2.dist-info/WHEEL
arc_alkali_rydberg_calculator-3.10.2.dist-info/top_level.txt
arc_alkali_rydberg_calculator-3.10.2.dist-info/RECORD
arc_alkali_rydberg_calculator-3.10.2.dist-info/licenses/LICENSE
