Metadata-Version: 2.4
Name: ARC-Alkali-Rydberg-Calculator
Version: 3.10.2
Summary: Alkali Rydberg Calculator
Author: Elizabeth J. Robertson, Jonathan D. Pritchard, Robert M. Potvliege, Matthew P. A. Jones, Charles S. Adams, Kevin J. Weatherill, and contributors
Author-email: Nikola Sibalic <nikolasibalic@physics.org>
License: BSD3
Project-URL: Homepage, https://atomcalc.org/
Project-URL: Repository, https://github.com/nikolasibalic/ARC-Alkali-Rydberg-Calculator
Project-URL: Documentation, https://arc-alkali-rydberg-calculator.readthedocs.io/en/latest/
Project-URL: Download, https://github.com/nikolasibalic/ARC-Alkali-Rydberg-Calculator/archive/refs/tags/v3.10.2.tar.gz
Keywords: rydberg,physics,stark maps,atom interactions,quantum optics,van der Waals,scientific,atomic sensors,quantum sensors,alkali atoms,alkaline atoms,divalent atoms,quantum computing
Classifier: Programming Language :: Python
Classifier: Programming Language :: Python :: 3
Classifier: Intended Audience :: Science/Research
Classifier: Intended Audience :: Education
Classifier: License :: OSI Approved :: BSD License
Classifier: Topic :: Scientific/Engineering
Classifier: Topic :: Scientific/Engineering :: Physics
Classifier: Development Status :: 5 - Production/Stable
Requires-Python: >=3.10
License-File: LICENSE
Requires-Dist: scipy>=1.15.0
Requires-Dist: numpy>=2.0
Requires-Dist: matplotlib>=1.5.3
Requires-Dist: sympy>=1.1.1
Requires-Dist: lmfit>=0.9.0
Requires-Dist: rich>=13.9.4
Requires-Dist: h5py>=3.11.0
Requires-Dist: asteval>=1.0.6
Dynamic: license-file
